distox.py
circuitpython_distox-1.0.0.dist-info/LICENSE
circuitpython_distox-1.0.0.dist-info/METADATA
circuitpython_distox-1.0.0.dist-info/WHEEL
circuitpython_distox-1.0.0.dist-info/top_level.txt
circuitpython_distox-1.0.0.dist-info/RECORD
