Metadata-Version: 2.1
Name: circuitpython-distox
Version: 1.0.0
Summary: DistoX Bluetooth Protocol
Author-email: Adafruit Industries <circuitpython@adafruit.com>
License: MIT
Project-URL: Homepage, https://github.com/furbrain/CircuitPython_distox
Keywords: adafruit,blinka,circuitpython,micropython,distox,disto,distox,bluetooth,cave,survey
Classifier: Intended Audience :: Developers
Classifier: Topic :: Software Development :: Libraries
Classifier: Topic :: Software Development :: Embedded Systems
Classifier: Topic :: System :: Hardware
Classifier: License :: OSI Approved :: MIT License
Classifier: Programming Language :: Python :: 3
License-File: LICENSE
Requires-Dist: Adafruit-Blinka
Provides-Extra: optional
Requires-Dist: adafruit-circuitpython-asyncio ; extra == 'optional'
